setup.py
teamrubber/__init__.py
teamrubber.recipe.portbase.egg-info/PKG-INFO
teamrubber.recipe.portbase.egg-info/SOURCES.txt
teamrubber.recipe.portbase.egg-info/dependency_links.txt
teamrubber.recipe.portbase.egg-info/entry_points.txt
teamrubber.recipe.portbase.egg-info/namespace_packages.txt
teamrubber.recipe.portbase.egg-info/not-zip-safe
teamrubber.recipe.portbase.egg-info/requires.txt
teamrubber.recipe.portbase.egg-info/top_level.txt
teamrubber/recipe/__init__.py
teamrubber/recipe/portbase/__init__.py