Metadata-Version: 1.1
Name: teamrubber.recipe.portbase
Version: 1.0
Summary: Magical buildout part which can be addressed using offsets to allow a base port
Home-page: UNKNOWN
Author: Alan Hoey
Author-email: alan.hoey@teamrubber.com
License: GPL
Platform: UNKNOWN
Classifier: Framework :: Buildout
Classifier: Intended Audience :: Developers
Classifier: Topic :: Software Development :: Build Tools
Classifier: Topic :: Software Development :: Libraries :: Python Modules
